filekits/__init__.py
filekits/base_io/__init__.py
filekits/base_io/down_load.py
filekits/base_io/folder.py
filekits/base_io/load.py
filekits/base_io/save.py
filekits/image/__init__.py
filekits/image/convert.py
filekits/image/draw.py
filekits/image/img_crop.py
filekits/image/img_fill.py
filekits/image/img_info.py
filekits/image/img_scale.py
filekits/utils/__init__.py
filekits/utils/dict_util.py
filekits-0.2.6.dist-info/licenses/LICENSE
filekits-0.2.6.dist-info/METADATA
filekits-0.2.6.dist-info/WHEEL
filekits-0.2.6.dist-info/top_level.txt
filekits-0.2.6.dist-info/RECORD
