Metadata-Version: 2.4
Name: filekits
Version: 0.2.6
Summary: Filekits - Python文件处理工具包，提供文件读写、网络下载、文件夹操作、图片处理等常用功能
Home-page: https://github.com/tinycen/filekits
Author: tinycen
Author-email: sky_ruocen@qq.com
Classifier: Programming Language :: Python :: 3
Classifier: License :: OSI Approved :: MIT License
Classifier: Operating System :: OS Independent
Requires-Python: >=3.10
License-File: LICENSE
Requires-Dist: pandas
Requires-Dist: openpyxl
Requires-Dist: pyyaml
Requires-Dist: funcguard
Requires-Dist: opencv-python
Requires-Dist: Pillow
Dynamic: author
Dynamic: author-email
Dynamic: classifier
Dynamic: description
Dynamic: description-content-type
Dynamic: home-page
Dynamic: license-file
Dynamic: requires-dist
Dynamic: requires-python
Dynamic: summary
